{"Models": {"NoName": {"HAs": {"NoName": {"lines": {"12": {"reset": "", "guard": "((y >= 1.8 and x <= 2.8) or (y <= 0.8 and x <= 2.8))", "rotation": 0.0, "style": 1, "strFromLocation": "L1", "strToLocation": "L2_End", "boxName": "12", "type": "Edge"}}, "name": "NoName", "variables": {"v1": {"isConstant": true, "isOutput": false, "isInput": false, "initialValue": "30", "boxName": "v1", "type": "Variable"}, "y": {"isConstant": false, "isOutput": false, "isInput": false, "initialValue": "1", "boxName": "y", "type": "Variable"}, "v2": {"isConstant": true, "isOutput": false, "isInput": false, "initialValue": "-10", "boxName": "v2", "type": "Variable"}, "phi": {"isConstant": false, "isOutput": false, "isInput": false, "initialValue": "1", "boxName": "phi", "type": "Variable"}, "theta": {"isConstant": false, "isOutput": false, "isInput": false, "initialValue": "0", "boxName": "theta", "type": "Variable"}, "x": {"isConstant": false, "isOutput": false, "isInput": false, "initialValue": "0", "boxName": "x", "type": "Variable"}, "le": {"isConstant": true, "isOutput": false, "isInput": false, "initialValue": "1", "boxName": "le", "type": "Variable"}}, "boxes": {"L1": {"isEnd": false, "isInitial": true, "rotation": 0.0, "size": [200.0, 110.0], "position": [358.0, 251.0], "invariant": "not ((y >= 1.8 and x <= 2.8) or (y <= 0.8 and x <= 2.8))", "isNameAbove": true, "checkPoints": {"3": {"VariableName": "y", "boxName": "3", "Value": "1.8"}, "2": {"VariableName": "y", "boxName": "2", "Value": "0.8"}, "1": {"VariableName": "x", "boxName": "1", "Value": "2.8"}}, "boxName": "L1", "type": "Location", "equation": ["$\\dot{x}=\\cos({\\theta})*v_1$", "$\\dot{y}=\\sin(\\theta)*v_1$", "$\\dot{\\theta}=\\tan(\\phi)/le\\times v_1$", "$\\dot{\\phi}=v_2$"]}, "L2_End": {"isEnd": true, "isInitial": false, "rotation": 0.0, "size": [200.0, 110.0], "position": [383.0, 479.0], "invariant": "((y >= 1.8 and x <= 2.8) or (y <= 0.8 and x <= 2.8))", "isNameAbove": false, "checkPoints": {}, "boxName": "L2_End", "type": "Location", "equation": [""]}}, "type": "HA"}}}}}